chamallow
