Metadata-Version: 2.1
Name: chamallow
Version: 0.1.1
Summary: Yet another yaml runner.
Home-page: https://gitlab.com/toopy/chamallow
Author: Florent Pigout
Author-email: florent@toopy.org
License: MIT
Keywords: yaml,runner
Platform: UNKNOWN
Classifier: Development Status :: 4 - Beta
Classifier: Intended Audience :: Developers
Classifier: License :: OSI Approved :: MIT License
Classifier: Natural Language :: English
Classifier: Programming Language :: Python :: 3.8
Provides-Extra: lint
Provides-Extra: release
Provides-Extra: test
Provides-Extra: zmq
License-File: LICENSE
